ypm/__init__.py
ypm-0.0.1.dist-info/LICENSE
ypm-0.0.1.dist-info/METADATA
ypm-0.0.1.dist-info/WHEEL
ypm-0.0.1.dist-info/RECORD
